readpy/__init__.py
readpy/read.py
readpy/write.py
test/__init__.py
test/test_read.py
test/test_write.py
readpy-0.0.1.dev2.dist-info/METADATA
readpy-0.0.1.dev2.dist-info/WHEEL
readpy-0.0.1.dev2.dist-info/top_level.txt
readpy-0.0.1.dev2.dist-info/RECORD
