Metadata-Version: 2.1
Name: readpy
Version: 0.0.1.dev2
Summary: A package designed to syntactically mimic the readr R package
Home-page: https://github.com/durrantmm/readpy
Author: Matt Durrant
Author-email: matthewgeorgedurrant@gmail.com
License: UNKNOWN
Keywords: readr R syntax
Platform: UNKNOWN
